tint/__init__.py
tint/core.py
tint_zaqar-0.0.2a0.dist-info/licenses/LICENSE
tint_zaqar-0.0.2a0.dist-info/METADATA
tint_zaqar-0.0.2a0.dist-info/WHEEL
tint_zaqar-0.0.2a0.dist-info/top_level.txt
tint_zaqar-0.0.2a0.dist-info/RECORD
