Metadata-Version: 2.4
Name: tint-zaqar
Version: 0.0.2a0
Summary: A lightweight Python library that adds color and style to your terminal output.
Author-email: zaqar <hakobyanzaqar3@gmail.com>
License: MIT
Project-URL: Homepage, https://github.com/yourusername/tint
Project-URL: Repository, https://github.com/yourusername/tint
Keywords: color,terminal,ansi,cli,styling
Classifier: Development Status :: 3 - Alpha
Classifier: Intended Audience :: Developers
Classifier: License :: OSI Approved :: MIT License
Classifier: Operating System :: OS Independent
Classifier: Programming Language :: Python :: 3
Classifier: Programming Language :: Python :: 3.7
Classifier: Programming Language :: Python :: 3.8
Classifier: Programming Language :: Python :: 3.9
Classifier: Programming Language :: Python :: 3.10
Classifier: Programming Language :: Python :: 3.11
Classifier: Programming Language :: Python :: 3.12
Classifier: Topic :: Software Development :: Libraries
Classifier: Topic :: Terminals
Requires-Python: >=3.7
License-File: LICENSE
Dynamic: license-file
